explorermenu/__init__.py
explorermenu/__main__.py
explorermenu/menu_items.py
explorer_menu-0.4.0.dist-info/LICENSE
explorer_menu-0.4.0.dist-info/METADATA
explorer_menu-0.4.0.dist-info/WHEEL
explorer_menu-0.4.0.dist-info/top_level.txt
explorer_menu-0.4.0.dist-info/RECORD
