Metadata-Version: 2.1
Name: explorer-menu
Version: 0.4.0
Summary: A python module to help creating explorer menus for Windows Explorer.
Home-page: https://github.com/andersonbrands/explorer-menu
Author: Anderson Brandao
Author-email: anderson.brands@gmail.com
License: UNKNOWN
Platform: UNKNOWN
Classifier: Programming Language :: Python :: 3
Classifier: License :: OSI Approved :: GNU General Public License v3 (GPLv3)
Classifier: Operating System :: Microsoft :: Windows
Requires-Python: >=3.6
